tui_dsg/__init__.py
tui_dsg/bereinigung/__init__.py
tui_dsg/bereinigung/tests.py
tui_dsg/beschaffung/__init__.py
tui_dsg/beschaffung/apis/__init__.py
tui_dsg/beschaffung/apis/tests.py
tui_dsg/beschaffung/dateien/__init__.py
tui_dsg/beschaffung/dateien/tests.py
tui_dsg/beschaffung/formate/__init__.py
tui_dsg/beschaffung/formate/tests.py
tui_dsg/beschaffung/html/__init__.py
tui_dsg/beschaffung/html/tests.py
tui_dsg/classification/__init__.py
tui_dsg/classification/decision_tree.py
tui_dsg/classification/nearest_neighbor.py
tui_dsg/classification/tests.py
tui_dsg/clustering/__init__.py
tui_dsg/clustering/dbscan.py
tui_dsg/clustering/kmeans.py
tui_dsg/clustering/tests.py
tui_dsg/datasets/__init__.py
tui_dsg/datasets/resources/banknote.csv
tui_dsg/datasets/resources/banknote_binary.csv
tui_dsg/datasets/resources/cast_array.csv.bz2
tui_dsg/datasets/resources/cast_data.csv
tui_dsg/datasets/resources/cast_graph.csv
tui_dsg/datasets/resources/cast_names.csv
tui_dsg/datasets/resources/clustering_example1.csv
tui_dsg/datasets/resources/clustering_example2.csv
tui_dsg/datasets/resources/company_sales.csv
tui_dsg/datasets/resources/company_sales_generator.py
tui_dsg/datasets/resources/component_graph.csv
tui_dsg/datasets/resources/connected_graph.csv
tui_dsg/datasets/resources/deutsche_nachnamen_haeufigkeit.txt
tui_dsg/datasets/resources/disney_plus_clustering.csv
tui_dsg/datasets/resources/disney_plus_popularity.csv
tui_dsg/datasets/resources/disney_plus_ratings.csv
tui_dsg/datasets/resources/disney_plus_titles.csv
tui_dsg/datasets/resources/disney_plus_titles.json
tui_dsg/datasets/resources/disney_plus_titles.pickle
tui_dsg/datasets/resources/disney_plus_titles_cast.json
tui_dsg/datasets/resources/disney_plus_titles_df.pickle
tui_dsg/datasets/resources/disney_plus_titles_director.csv
tui_dsg/datasets/resources/disney_plus_titles_extended.csv
tui_dsg/datasets/resources/disney_plus_titles_jun22.txt
tui_dsg/datasets/resources/disney_plus_titles_jun22.txt.bz2
tui_dsg-202509050851.dist-info/METADATA
tui_dsg-202509050851.dist-info/WHEEL
tui_dsg-202509050851.dist-info/top_level.txt
tui_dsg-202509050851.dist-info/RECORD
