Metadata-Version: 2.4
Name: tui_dsg
Version: 202509050851
Summary: everything you need for our jupyter notebooks
Home-page: https://dbgit.prakinf.tu-ilmenau.de/lectures/data-science-grundlagen
Author: Eric Tröbs
Author-email: eric.troebs@tu-ilmenau.de
Classifier: Programming Language :: Python :: 3
Classifier: License :: OSI Approved :: MIT License
Classifier: Operating System :: OS Independent
Requires-Python: >=3.10
Requires-Dist: jupyter
Requires-Dist: ipywidgets
Requires-Dist: checkmarkandcross
Requires-Dist: jupyter-duckdb>=1.2.101
Requires-Dist: beautifulsoup4~=4.12
Requires-Dist: kaleido~=1.0
Requires-Dist: matplotlib~=3.10
Requires-Dist: networkx~=3.5
Requires-Dist: nltk~=3.9
Requires-Dist: numpy~=1.26
Requires-Dist: pandas~=2.2
Requires-Dist: pillow~=11.1
Requires-Dist: plotly~=6.1
Requires-Dist: pyyaml~=6.0
Requires-Dist: requests~=2.32
Requires-Dist: scikit-learn~=1.6
Requires-Dist: scipy~=1.13
Requires-Dist: torch~=2.6
Requires-Dist: transformers~=4.50
Requires-Dist: gensim~=4.3.3
Requires-Dist: geopandas~=1.1.0
Requires-Dist: pygwalker~=0.4.9
Requires-Dist: spacy~=3.8.4
Requires-Dist: statsmodels~=0.14.4
Requires-Dist: fa2_modified==0.3.10
Requires-Dist: grizzly_sql==0.1.5.post1
Requires-Dist: HanTa==1.1.2
Requires-Dist: Levenshtein==0.27.1
Dynamic: author
Dynamic: author-email
Dynamic: classifier
Dynamic: description
Dynamic: description-content-type
Dynamic: home-page
Dynamic: requires-dist
Dynamic: requires-python
Dynamic: summary
